simplepe/__init__.py
simplepe/randpe.py
simplepe/rope.py
simplepe/sinpe.py
simplepe-0.0.3.dist-info/LICENSE
simplepe-0.0.3.dist-info/METADATA
simplepe-0.0.3.dist-info/WHEEL
simplepe-0.0.3.dist-info/top_level.txt
simplepe-0.0.3.dist-info/RECORD
