Metadata-Version: 2.1
Name: simplepe
Version: 0.0.3
Summary: A simple simplepe for positional encoding
Home-page: https://github.com/donglinkang2021/simplepe
Author: Dong Linkang
Author-email: donglinkang2021@163.com
License: UNKNOWN
Keywords: artificial intelligence,deep learning,positional embedding
Platform: UNKNOWN
Classifier: Programming Language :: Python :: 3.9
Classifier: License :: OSI Approved :: MIT License
Classifier: Operating System :: OS Independent
License-File: LICENSE
Requires-Dist: torch>=2.0
